{"config_name": "recursive_grid_0days",
 "logging_level": 0,
 "long": {"auto_unstuck_ema_dist": 0,
          "auto_unstuck_wallet_exposure_threshold": 0,
          "backwards_tp": false,
          "ddown_factor": 1.370300413866786,
          "ema_span_0": 254.84220584674534,
          "ema_span_1": 663.8542928418992,
          "enabled": true,
          "initial_eprice_ema_dist": -0.26418581239961747,
          "initial_qty_pct": 0.00966655512790075,
          "markup_range": 0.03311365356961269,
          "min_markup": 0.0051792837969031474,
          "n_close_orders": 5,
          "rentry_pprice_dist": 0.034152103922233674,
          "rentry_pprice_dist_wallet_exposure_weighting": 0,
          "wallet_exposure_limit": 0.2},
 "short": {"auto_unstuck_ema_dist": 0.004395928522424467,
           "auto_unstuck_wallet_exposure_threshold": 0.06979890864546409,
           "backwards_tp": true,
           "ddown_factor": 0.39684580781764645,
           "ema_span_0": 1728.2519361176717,
           "ema_span_1": 7839.920832864107,
           "enabled": false,
           "initial_eprice_ema_dist": -0.09038823137733655,
           "initial_qty_pct": 0.015,
           "markup_range": 0.011947642273989159,
           "min_markup": 0.00334185837782849,
           "n_close_orders": 10,
           "rentry_pprice_dist": 0.04119849578955309,
           "rentry_pprice_dist_wallet_exposure_weighting": 29.81564843435838,
           "wallet_exposure_limit": 0.1}}