{"config_name": "clock_0days",
 "long": {"backwards_tp": true,
          "delay_between_fills_minutes_close": 1100.360544943159,
          "delay_between_fills_minutes_entry": 1440,
          "delay_weight_close": 0,
          "delay_weight_entry": 23.7636553485191,
          "ema_dist_close": 0.003,
          "ema_dist_entry": 0.001249916742069134,
          "ema_span_0": 613.1443101709993,
          "ema_span_1": 1313.9546642492644,
          "enabled": true,
          "markup_range": 0.005768893093261989,
          "min_markup": 0.0038518779478720587,
          "n_close_orders": 3,
          "qty_pct_close": 0.012371373031822178,
          "qty_pct_entry": 0.016761655919047012,
          "wallet_exposure_limit": 0.5,
          "we_multiplier_close": 0,
          "we_multiplier_entry": 143.33815089987323},
 "short": {"backwards_tp": true,
           "delay_between_fills_minutes_close": 1288.038206954278,
           "delay_between_fills_minutes_entry": 621.6464707977761,
           "delay_weight_close": 0,
           "delay_weight_entry": 7.021438108044898,
           "ema_dist_close": 0.0015897776315596667,
           "ema_dist_entry": -0.002662947523389305,
           "ema_span_0": 1074.2815493391274,
           "ema_span_1": 1440,
           "enabled": true,
           "markup_range": 0.0053027522223502085,
           "min_markup": 0.009668834268686295,
           "n_close_orders": 12,
           "qty_pct_close": 0.011748889376177334,
           "qty_pct_entry": 0.010030819991418844,
           "wallet_exposure_limit": 0.25,
           "we_multiplier_close": 0,
           "we_multiplier_entry": 38.76631721190522}}