{"config_name": "clock_0days",
 "long": {"backwards_tp": true,
          "delay_between_fills_minutes_close": 698.5408796306258,
          "delay_between_fills_minutes_entry": 963.1885900970692,
          "delay_weight_close": 76.93210033826122,
          "delay_weight_entry": 22.14146269199931,
          "ema_dist_close": -0.0036242894646853615,
          "ema_dist_entry": -0.00048566399682911806,
          "ema_span_0": 1412.4931144119912,
          "ema_span_1": 1376.5665204843417,
          "enabled": true,
          "markup_range": 0.007733571387961141,
          "min_markup": 0.007489340820359696,
          "n_close_orders": 9,
          "qty_pct_close": 0.07145055405311829,
          "qty_pct_entry": 0.01236324458938418,
          "wallet_exposure_limit": 0.5,
          "we_multiplier_close": 2.567555088790148,
          "we_multiplier_entry": 91.09943470562327},
 "short": {"backwards_tp": true,
           "delay_between_fills_minutes_close": 1415.598447063892,
           "delay_between_fills_minutes_entry": 974.0094793775555,
           "delay_weight_close": 1.8331472150696526,
           "delay_weight_entry": 65.08831945896438,
           "ema_dist_close": -0.015133652773124916,
           "ema_dist_entry": -0.03186015245517462,
           "ema_span_0": 52.96847563912863,
           "ema_span_1": 1057.4314298913148,
           "enabled": false,
           "markup_range": 0.026899113292986505,
           "min_markup": 0.00759051018958263,
           "n_close_orders": 15,
           "qty_pct_close": 0.014066802398759584,
           "qty_pct_entry": 0.01373012347996502,
           "wallet_exposure_limit": 1.0,
           "we_multiplier_close": 10.557733178350281,
           "we_multiplier_entry": 31.97230039151747}}