{"config_name": "recursive_grid_0days",
 "logging_level": 0,
 "long": {"auto_unstuck_ema_dist": 0,
          "auto_unstuck_wallet_exposure_threshold": 0,
          "backwards_tp": false,
          "ddown_factor": 2.5036554393950503,
          "ema_span_0": 83.08275268102712,
          "ema_span_1": 49.07052087128136,
          "enabled": true,
          "initial_eprice_ema_dist": -0.1,
          "initial_qty_pct": 0.0028579531417498964,
          "markup_range": 0.039120095977823746,
          "min_markup": 0.004753241266710872,
          "n_close_orders": 2,
          "rentry_pprice_dist": 0.028604819029662686,
          "rentry_pprice_dist_wallet_exposure_weighting": 0,
          "wallet_exposure_limit": 0.2},
 "short": {"auto_unstuck_ema_dist": 0.0565601996639564,
           "auto_unstuck_wallet_exposure_threshold": 0.03218254403987014,
           "backwards_tp": true,
           "ddown_factor": 2.098051496739285,
           "ema_span_0": 1584.5506670940943,
           "ema_span_1": 2548.223081621464,
           "enabled": false,
           "initial_eprice_ema_dist": -0.05653988772974776,
           "initial_qty_pct": 0.015,
           "markup_range": 0.022846790250849666,
           "min_markup": 0.003628365372166168,
           "n_close_orders": 5,
           "rentry_pprice_dist": 0.0191364779435661,
           "rentry_pprice_dist_wallet_exposure_weighting": 35.1169881280368,
           "wallet_exposure_limit": 0.1}}
