{"config_name": "recursive_grid_0days",
 "logging_level": 0,
 "long": {"auto_unstuck_ema_dist": -0.0021519425390829896,
          "auto_unstuck_wallet_exposure_threshold": 0.06408176050569775,
          "backwards_tp": true,
          "ddown_factor": 0.603828231677181,
          "ema_span_0": 149.55029936999787,
          "ema_span_1": 667.6012524673253,
          "enabled": true,
          "initial_eprice_ema_dist": 0.004734419364069495,
          "initial_qty_pct": 0.01,
          "markup_range": 0.0029591023140512827,
          "min_markup": 0.0039657297448673365,
          "n_close_orders": 2,
          "rentry_pprice_dist": 0.025994584599945508,
          "rentry_pprice_dist_wallet_exposure_weighting": 1.463462048508012,
          "wallet_exposure_limit": 1},
 "short": {"auto_unstuck_ema_dist": -0.09042808201628436,
           "auto_unstuck_wallet_exposure_threshold": 0.06228012093943081,
           "backwards_tp": true,
           "ddown_factor": 3,
           "ema_span_0": 655.0583660337782,
           "ema_span_1": 494.2946916691794,
           "enabled": false,
           "initial_eprice_ema_dist": -0.08985597492976037,
           "initial_qty_pct": 0.01,
           "markup_range": 0.012151614291644415,
           "min_markup": 0.004218955664146525,
           "n_close_orders": 8,
           "rentry_pprice_dist": 0.04097848938443242,
           "rentry_pprice_dist_wallet_exposure_weighting": 29.59841639981122,
           "wallet_exposure_limit": 1.0}}