{"config_name": "clock_0days",
 "long": {"backwards_tp": true,
          "delay_between_fills_minutes_close": 1346.6926773461869,
          "delay_between_fills_minutes_entry": 875.0838109598636,
          "delay_weight_close": 1.2990498571629565,
          "delay_weight_entry": 21.583094314793115,
          "ema_dist_close": -0.006477516496616198,
          "ema_dist_entry": -0.0013743626999055609,
          "ema_span_0": 1358.1684793908698,
          "ema_span_1": 625.7221904687372,
          "enabled": true,
          "markup_range": 0.0026969980129132698,
          "min_markup": 0.00913371258296115,
          "n_close_orders": 4,
          "qty_pct_close": 0.033575109333444965,
          "qty_pct_entry": 0.010918587724741798,
          "wallet_exposure_limit": 0.6,
          "we_multiplier_close": 0,
          "we_multiplier_entry": 71.35721642989503},
 "short": {"backwards_tp": true,
           "delay_between_fills_minutes_close": 1222.58703546962,
           "delay_between_fills_minutes_entry": 1189.879658020506,
           "delay_weight_close": 0,
           "delay_weight_entry": 15.06797621160764,
           "ema_dist_close": 0.003,
           "ema_dist_entry": 0.0014049283289814516,
           "ema_span_0": 1400.3184371905588,
           "ema_span_1": 37.82083273296957,
           "enabled": true,
           "markup_range": 0.003285510528706678,
           "min_markup": 0.002170513485342607,
           "n_close_orders": 10,
           "qty_pct_close": 0.014995064611210394,
           "qty_pct_entry": 0.038381197531105325,
           "wallet_exposure_limit": 0.18,
           "we_multiplier_close": 0,
           "we_multiplier_entry": 40.80839740445515}}