{"config_name": "clock_0days",
 "long": {"backwards_tp": true,
          "delay_between_fills_minutes_close": 96.66818906471764,
          "delay_between_fills_minutes_entry": 957.8255513913813,
          "delay_weight_close": 23.276029234402735,
          "delay_weight_entry": 15.09595348901127,
          "ema_dist_close": 0.004711305274343628,
          "ema_dist_entry": 0.0068909091462030945,
          "ema_span_0": 82.76518724631073,
          "ema_span_1": 664.2772659788536,
          "enabled": true,
          "markup_range": 0.008914076159635742,
          "min_markup": 0.06994597532350189,
          "n_close_orders": 14,
          "qty_pct_close": 0.3109290859178319,
          "qty_pct_entry": 0.02200341802112504,
          "wallet_exposure_limit": 1,
          "we_multiplier_close": 0,
          "we_multiplier_entry": 98.37026306665688},
 "short": {"backwards_tp": true,
           "delay_between_fills_minutes_close": 44.15241660002109,
           "delay_between_fills_minutes_entry": 1312.475528685527,
           "delay_weight_close": 26.623951539840263,
           "delay_weight_entry": 50.53983806113509,
           "ema_dist_close": -0.04033049802608232,
           "ema_dist_entry": -0.006271397538290632,
           "ema_span_0": 250.84918753601545,
           "ema_span_1": 1055.17238740576,
           "enabled": false,
           "markup_range": 0.01563607368132437,
           "min_markup": 0.05118517561572595,
           "n_close_orders": 13,
           "qty_pct_close": 0.5678587061942003,
           "qty_pct_entry": 0.38334147848695876,
           "wallet_exposure_limit": 1,
           "we_multiplier_close": 0.22835059141407155,
           "we_multiplier_entry": 69.10743020162847}}