{"config_name": "clock_0days",
 "long": {"backwards_tp": true,
          "delay_between_fills_minutes_close": 295.7618871699672,
          "delay_between_fills_minutes_entry": 1394.7790039429144,
          "delay_weight_close": 0,
          "delay_weight_entry": 23.431598277142058,
          "ema_dist_close": -0.005617231733770024,
          "ema_dist_entry": 0.003,
          "ema_span_0": 268.25383232705843,
          "ema_span_1": 1252.3031089704477,
          "enabled": true,
          "markup_range": 0.019295945883143335,
          "min_markup": 0.009456440778404627,
          "n_close_orders": 14,
          "qty_pct_close": 0.02975487827783852,
          "qty_pct_entry": 0.01,
          "wallet_exposure_limit": 0.6,
          "we_multiplier_close": 0.0,
          "we_multiplier_entry": 1.2797496977550393},
 "short": {"backwards_tp": true,
           "delay_between_fills_minutes_close": 1301.880400778087,
           "delay_between_fills_minutes_entry": 996.461900717381,
           "delay_weight_close": 0,
           "delay_weight_entry": 27.83817258802841,
           "ema_dist_close": -0.0034967466612210486,
           "ema_dist_entry": -0.0026949178370367297,
           "ema_span_0": 1404.3946047194804,
           "ema_span_1": 85.74283705175785,
           "enabled": true,
           "markup_range": 0.0022742239601034908,
           "min_markup": 0.008417758022046005,
           "n_close_orders": 4,
           "qty_pct_close": 0.019017523018471337,
           "qty_pct_entry": 0.022245127519415372,
           "wallet_exposure_limit": 0.18,
           "we_multiplier_close": 0,
           "we_multiplier_entry": 20.75950411170233}}