{"config_name": "recursive_grid_0days",
 "logging_level": 0,
 "long": {"auto_unstuck_ema_dist": 0.005,
          "auto_unstuck_wallet_exposure_threshold": 0.05451035546607686,
          "backwards_tp": true,
          "ddown_factor": 2.9009413230940435,
          "ema_span_0": 161.30296231416727,
          "ema_span_1": 579.9265306208906,
          "enabled": true,
          "initial_eprice_ema_dist": -0.1,
          "initial_qty_pct": 0.010822466497316222,
          "markup_range": 0.006775338861933883,
          "min_markup": 0.006382360327881511,
          "n_close_orders": 3,
          "rentry_pprice_dist": 0.0484478737586473,
          "rentry_pprice_dist_wallet_exposure_weighting": 0.0,
          "wallet_exposure_limit": 1},
 "short": {"auto_unstuck_ema_dist": -0.04476882215248458,
           "auto_unstuck_wallet_exposure_threshold": 0.07094064335433453,
           "backwards_tp": true,
           "ddown_factor": 1.70523023173928,
           "ema_span_0": 229.54181871690577,
           "ema_span_1": 344.1556182470447,
           "enabled": false,
           "initial_eprice_ema_dist": -0.0031665851105776716,
           "initial_qty_pct": 0.030694137644112753,
           "markup_range": 0.05961234904527629,
           "min_markup": 0.0010238213026474072,
           "n_close_orders": 2,
           "rentry_pprice_dist": 0.018051345171555842,
           "rentry_pprice_dist_wallet_exposure_weighting": 34.2178062699982,
           "wallet_exposure_limit": 1.0}}