{"config_name": "clock_0days",
 "long": {"backwards_tp": true,
          "delay_between_fills_minutes_close": 1014.8335847624194,
          "delay_between_fills_minutes_entry": 1106.7733366555524,
          "delay_weight_close": 0,
          "delay_weight_entry": 30.07418739420575,
          "ema_dist_close": -0.013346775935616013,
          "ema_dist_entry": 0.003,
          "ema_span_0": 1247.2968437763093,
          "ema_span_1": 1352.2047877758143,
          "enabled": true,
          "markup_range": 0.007356299089719656,
          "min_markup": 0.009597903969422502,
          "n_close_orders": 4,
          "qty_pct_close": 0.018187091121938226,
          "qty_pct_entry": 0.01,
          "wallet_exposure_limit": 0.6,
          "we_multiplier_close": 0,
          "we_multiplier_entry": 48.6239812852547},
 "short": {"backwards_tp": true,
           "delay_between_fills_minutes_close": 1004.2290401064403,
           "delay_between_fills_minutes_entry": 1438.635770650923,
           "delay_weight_close": 0,
           "delay_weight_entry": 16.65483005647458,
           "ema_dist_close": -0.0010939100299043065,
           "ema_dist_entry": 0.003,
           "ema_span_0": 791.3666209030666,
           "ema_span_1": 1363.646078822228,
           "enabled": true,
           "markup_range": 0.013103753593639116,
           "min_markup": 0.004278294456297361,
           "n_close_orders": 3,
           "qty_pct_close": 0.027172189330724426,
           "qty_pct_entry": 0.020469701469676405,
           "wallet_exposure_limit": 0.18,
           "we_multiplier_close": 0,
           "we_multiplier_entry": 111.05578180179798}}