{"config_name": "clock_0days",
 "long": {"backwards_tp": true,
          "delay_between_fills_minutes_close": 1255.0155509745136,
          "delay_between_fills_minutes_entry": 1377.72040141952,
          "delay_weight_close": 164.64628267310525,
          "delay_weight_entry": 12.941816955163677,
          "ema_dist_close": -0.01307740073048475,
          "ema_dist_entry": -0.0015628562658871828,
          "ema_span_0": 628.013307816489,
          "ema_span_1": 1285.9272418984788,
          "enabled": true,
          "markup_range": 0.010783002637949176,
          "min_markup": 0.009444783563610316,
          "n_close_orders": 11,
          "qty_pct_close": 0.018789462967989817,
          "qty_pct_entry": 0.01498930313316836,
          "wallet_exposure_limit": 0.25,
          "we_multiplier_close": 0,
          "we_multiplier_entry": 122.7372657246648},
 "short": {"backwards_tp": true,
           "delay_between_fills_minutes_close": 1378.5964866693273,
           "delay_between_fills_minutes_entry": 226.14692558661997,
           "delay_weight_close": 165.65312158488337,
           "delay_weight_entry": 4.06280763540584,
           "ema_dist_close": -0.0005017175738684294,
           "ema_dist_entry": -0.0061357350485446785,
           "ema_span_0": 1346.0923146686646,
           "ema_span_1": 1029.9716656193104,
           "enabled": true,
           "markup_range": 0.03392453369675054,
           "min_markup": 0.004026361021375886,
           "n_close_orders": 2,
           "qty_pct_close": 0.01496383467994774,
           "qty_pct_entry": 0.011606282296407255,
           "wallet_exposure_limit": 0.125,
           "we_multiplier_close": 0,
           "we_multiplier_entry": 0}}