{"config_name": "recursive_grid_0days",
 "logging_level": 0,
 "long": {"auto_unstuck_ema_dist": -6.768132217102086e-05,
          "auto_unstuck_wallet_exposure_threshold": 0.09481657019445157,
          "backwards_tp": true,
          "ddown_factor": 2.9046810370123146,
          "ema_span_0": 708.6935985536918,
          "ema_span_1": 823.8715101378755,
          "enabled": true,
          "initial_eprice_ema_dist": 0.01,
          "initial_qty_pct": 0.02131254463709359,
          "markup_range": 0.023905087266838727,
          "min_markup": 0.009981212737989312,
          "n_close_orders": 1,
          "rentry_pprice_dist": 0.033104896781834356,
          "rentry_pprice_dist_wallet_exposure_weighting": 1.8597773591768925,
          "wallet_exposure_limit": 1},
 "short": {"auto_unstuck_ema_dist": -0.056268883109266324,
           "auto_unstuck_wallet_exposure_threshold": 0.03028570284757646,
           "backwards_tp": true,
           "ddown_factor": 2.4467093303164167,
           "ema_span_0": 500.1459781574635,
           "ema_span_1": 335.7058704438736,
           "enabled": false,
           "initial_eprice_ema_dist": -0.07367132332741218,
           "initial_qty_pct": 0.09195361181379297,
           "markup_range": 0.04400044798003636,
           "min_markup": 0.006348991624449863,
           "n_close_orders": 10,
           "rentry_pprice_dist": 0.012261979759924442,
           "rentry_pprice_dist_wallet_exposure_weighting": 33.60854350420556,
           "wallet_exposure_limit": 1.0}}