{"config_name": "recursive_grid_0days",
 "logging_level": 0,
 "long": {"auto_unstuck_ema_dist": -0.009284419588238032,
          "auto_unstuck_wallet_exposure_threshold": 0.0466551636775442,
          "backwards_tp": true,
          "ddown_factor": 1.1212272094912084,
          "ema_span_0": 203.70771333827562,
          "ema_span_1": 933.1685930377489,
          "enabled": true,
          "initial_eprice_ema_dist": 0.0035767578635347284,
          "initial_qty_pct": 0.011063861992867685,
          "markup_range": 0.003965289145253069,
          "min_markup": 0.002157787662574813,
          "n_close_orders": 2,
          "rentry_pprice_dist": 0.02818212491636365,
          "rentry_pprice_dist_wallet_exposure_weighting": 2.8251217137706055,
          "wallet_exposure_limit": 1},
 "short": {"auto_unstuck_ema_dist": -0.01886017294633388,
           "auto_unstuck_wallet_exposure_threshold": 0.06102352506795955,
           "backwards_tp": true,
           "ddown_factor": 1.7489871087575877,
           "ema_span_0": 190.06997136142897,
           "ema_span_1": 981.5730944062828,
           "enabled": false,
           "initial_eprice_ema_dist": -0.03924486215690956,
           "initial_qty_pct": 0.08810007276527082,
           "markup_range": 0.02683799741671994,
           "min_markup": 0.0018548284845055787,
           "n_close_orders": 8,
           "rentry_pprice_dist": 0.04206045148482399,
           "rentry_pprice_dist_wallet_exposure_weighting": 1.873160679177786,
           "wallet_exposure_limit": 1.0}}