{"config_name": "clock_0days",
 "long": {"backwards_tp": true,
          "delay_between_fills_minutes_close": 1202.0570555768784,
          "delay_between_fills_minutes_entry": 1091.9861018506278,
          "delay_weight_close": 160.55096307577784,
          "delay_weight_entry": 21.461314095652725,
          "ema_dist_close": -0.022103242358096055,
          "ema_dist_entry": 0.003,
          "ema_span_0": 189.72851220764784,
          "ema_span_1": 854.1340745783828,
          "enabled": true,
          "markup_range": 0.03615260851044875,
          "min_markup": 0.01,
          "n_close_orders": 15,
          "qty_pct_close": 0.013044117702774385,
          "qty_pct_entry": 0.011653248645858682,
          "wallet_exposure_limit": 0.25,
          "we_multiplier_close": 0,
          "we_multiplier_entry": 23.750715781491945},
 "short": {"backwards_tp": true,
           "delay_between_fills_minutes_close": 1347.1141703170379,
           "delay_between_fills_minutes_entry": 867.6393039731178,
           "delay_weight_close": 89.0895755152926,
           "delay_weight_entry": 10.820132962969316,
           "ema_dist_close": -0.010509065472786804,
           "ema_dist_entry": 0.0014987051399733748,
           "ema_span_0": 421.63259888478206,
           "ema_span_1": 1373.7474640578512,
           "enabled": true,
           "markup_range": 0.007454473934105654,
           "min_markup": 0.009287988422185457,
           "n_close_orders": 7,
           "qty_pct_close": 0.02592683926641037,
           "qty_pct_entry": 0.016858243401548175,
           "wallet_exposure_limit": 0.125,
           "we_multiplier_close": 0,
           "we_multiplier_entry": 92.07980339667525}}